pasttense/__init__.py
pasttense/pasttense.py
pasttense/past_tense/__init__.py
pasttense/past_tense/past_tense.py
pasttense-3.3.0.dist-info/LICENSE
pasttense-3.3.0.dist-info/METADATA
pasttense-3.3.0.dist-info/WHEEL
pasttense-3.3.0.dist-info/top_level.txt
pasttense-3.3.0.dist-info/RECORD
